wakachigaki/__init__.py
wakachigaki/_tokenize.py
wakachigaki/feature/__init__.py
wakachigaki/feature/_char.py
wakachigaki/feature/_feature.py
wakachigaki/feature/_regexp.py
wakachigaki/hash/__init__.py
wakachigaki/hash/_crc32.py
wakachigaki/hash/_hash.py
wakachigaki/model/__init__.py
wakachigaki/model/_model.py
wakachigaki/predict/__init__.py
wakachigaki/predict/_predict.py
wakachigaki/predict/_proba.py
wakachigaki/util/__init__.py
wakachigaki/util/_ngram.py
wakachigaki/util/_normalize.py
wakachigaki/util/_sigmoid.py
wakachigaki-1.3.3.dist-info/LICENSE
wakachigaki-1.3.3.dist-info/METADATA
wakachigaki-1.3.3.dist-info/WHEEL
wakachigaki-1.3.3.dist-info/top_level.txt
wakachigaki-1.3.3.dist-info/RECORD
