Metadata-Version: 2.1
Name: wakachigaki
Version: 1.3.3
Summary: 6.2Kbの軽量日本語分かち書きライブラリ
Home-page: https://github.com/yuhsak/wakachigaki-py
Author: Yuhsak Inoue
Author-email: yuhsak.inoue@gmail.com
Maintainer: Yuhsak Inoue
Maintainer-email: yuhsak.inoue@gmail.com
License: MIT
Download-URL: https://github.com/yuhsak/wakachigaki-py
Platform: UNKNOWN
License-File: LICENSE
